{"playlist":{"subscribers":[{"defaultAvatar":false,"province":500000,"authStatus":0,"followed":false,"avatarUrl":"http://p1.music.126.net/GjV9SvXikcbPaqMgUCFIVw==/3439272373286390.jpg","accountStatus":0,"gender":1,"city":500101,"birthday":842545333721,"userId":281525731,"userType":0,"nickname":"骄傲的杨大大","signature":"","description":"","detailDescription":"","avatarImgId":3439272373286390,"backgroundImgId":2002210674180200,"backgroundUrl":"http://p1.music.126.net/45Nu4EqvFqK_kQj6BkPwcw==/2002210674180200.jpg","authority":0,"mutual":false,"expertTags":null,"experts":null,"djStatus":0,"vipType":0,"remarkName":null,"avatarImgIdStr":"3439272373286390","backgroundImgIdStr":"2002210674180200"},{"defaultAvatar":false,"province":440000,"authStatus":0,"followed":false,"avatarUrl":"http://p1.music.126.net/o5aJS1GZloeAXcpf06qgNQ==/109951163127534547.jpg","accountStatus":0,"gender":1,"city":441300,"birthday":1031390371928,"userId":378297598,"userType":0,"nickname":"咸鱼琪亚娜","signature":"我去寻找崩坏的本源了","description":"","detailDescription":"","avatarImgId":109951163127534540,"backgroundImgId":2002210674180198,"backgroundUrl":"http://p1.music.126.net/i0qi6mibX8gq2SaLF1bYbA==/2002210674180198.jpg","authority":0,"mutual":false,"expertTags":null,"experts":null,"djStatus":0,"vipType":0,"remarkName":null,"avatarImgIdStr":"109951163127534547","backgroundImgIdStr":"2002210674180198","avatarImgId_str":"109951163127534547"},{"defaultAvatar":false,"province":520000,"authStatus":0,"followed":false,"avatarUrl":"http://p1.music.126.net/s2Qf-LWGdS4t2-OdLyqfzg==/109951163522512887.jpg","accountStatus":0,"gender":1,"city":522400,"birthday":-2209017600000,"userId":255251529,"userType":0,"nickname":"2902180416","signature":"","description":"","detailDescription":"","avatarImgId":109951163522512880,"backgroundImgId":18917097556255850,"backgroundUrl":"http://p1.music.126.net/580wA8uHyMId4NBdvqrWnw==/18917097556255850.jpg","authority":0,"mutual":false,"expertTags":null,"experts":null,"djStatus":0,"vipType":0,"remarkName":null,"avatarImgIdStr":"109951163522512887","backgroundImgIdStr":"18917097556255850","avatarImgId_str":"109951163522512887"},{"defaultAvatar":false,"province":410000,"authStatus":0,"followed":false,"avatarUrl":"http://p1.music.126.net/U-sbsU0a4Ekw3oUNdLXlwg==/3393092916249648.jpg","accountStatus":0,"gender":2,"city":410800,"birthday":-2209017600000,"userId":341349129,"userType":0,"nickname":"Amber啦啦啦-","signature":"","description":"","detailDescription":"","avatarImgId":3393092916249648,"backgroundImgId":2002210674180200,"backgroundUrl":"http://p1.music.126.net/45Nu4EqvFqK_kQj6BkPwcw==/2002210674180200.jpg","authority":0,"mutual":false,"expertTags":null,"experts":null,"djStatus":0,"vipType":0,"remarkName":null,"avatarImgIdStr":"3393092916249648","backgroundImgIdStr":"2002210674180200"},{"defaultAvatar":false,"province":430000,"authStatus":0,"followed":false,"avatarUrl":"http://p1.music.126.net/HNDIr31Sd9sfJCeMNkWxVw==/18954480951701324.jpg","accountStatus":0,"gender":1,"city":430900,"birthday":-2209017600000,"userId":560873725,"userType":0,"nickname":"套路170807","signature":"","description":"","detailDescription":"","avatarImgId":18954480951701324,"backgroundImgId":109951162868128400,"backgroundUrl":"http://p1.music.126.net/2zSNIqTcpHL2jIvU6hG0EA==/109951162868128395.jpg","authority":0,"mutual":false,"expertTags":null,"experts":null,"djStatus":0,"vipType":0,"remarkName":null,"avatarImgIdStr":"18954480951701324","backgroundImgIdStr":"109951162868128395","avatarImgId_str":"18954480951701324"},{"defaultAvatar":false,"province":370000,"authStatus":0,"followed":false,"avatarUrl":"http://p1.music.126.net/HJcuKiAm_Aca0X8dQwuk4g==/109951162853766547.jpg","accountStatus":0,"gender":0,"city":370800,"birthday":-2209017600000,"userId":413365951,"userType":0,"nickname":"毁溺-","signature":"","description":"","detailDescription":"","avatarImgId":109951162853766540,"backgroundImgId":2002210674180203,"backgroundUrl":"http://p1.music.126.net/bmA_ablsXpq3Tk9HlEg9sA==/2002210674180203.jpg","authority":0,"mutual":false,"expertTags":null,"experts":null,"djStatus":0,"vipType":0,"remarkName":null,"avatarImgIdStr":"109951162853766547","backgroundImgIdStr":"2002210674180203","avatarImgId_str":"109951162853766547"},{"defaultAvatar":false,"province":440000,"authStatus":0,"followed":false,"avatarUrl":"http://p1.music.126.net/8-Oj43hqB9LBnGsvWlgAig==/109951163060967508.jpg","accountStatus":0,"gender":2,"city":440300,"birthday":951040013465,"userId":308674548,"userType":0,"nickname":"一枚大可爱呐","signature":"比你酷","description":"","detailDescription":"","avatarImgId":109951163060967500,"backgroundImgId":109951162993867680,"backgroundUrl":"http://p1.music.126.net/w5oxJPkkMpzhBiM1PGf7ww==/109951162993867678.jpg","authority":0,"mutual":false,"expertTags":null,"experts":null,"djStatus":0,"vipType":10,"remarkName":null,"avatarImgIdStr":"109951163060967508","backgroundImgIdStr":"109951162993867678","avatarImgId_str":"109951163060967508"},{"defaultAvatar":false,"province":370000,"authStatus":0,"followed":false,"avatarUrl":"http://p1.music.126.net/fi6IK9RsW7W66QdSYsWToA==/109951163516956698.jpg","accountStatus":0,"gender":2,"city":370100,"birthday":-2209017600000,"userId":1573832956,"userType":0,"nickname":"归来仍是少年107","signature":"","description":"","detailDescription":"","avatarImgId":109951163516956700,"backgroundImgId":109951162868128400,"backgroundUrl":"http://p1.music.126.net/2zSNIqTcpHL2jIvU6hG0EA==/109951162868128395.jpg","authority":0,"mutual":false,"expertTags":null,"experts":null,"djStatus":0,"vipType":0,"remarkName":null,"avatarImgIdStr":"109951163516956698","backgroundImgIdStr":"109951162868128395","avatarImgId_str":"109951163516956698"}],"subscribed":false,"creator":{"defaultAvatar":false,"province":530000,"authStatus":0,"followed":false,"avatarUrl":"http://p1.music.126.net/gBB-7d6GJU5S_WAazI91hg==/109951163029169199.jpg","accountStatus":0,"gender":2,"city":530100,"birthday":1464796800000,"userId":289477415,"userType":0,"nickname":"AirRadio空气赫兹","signature":"Dreamer On Air & Dreaming With You 电台 / 歌单 / 专栏 / 资讯","description":"","detailDescription":"","avatarImgId":109951163029169200,"backgroundImgId":109951163023977360,"backgroundUrl":"http://p1.music.126.net/nfc4KK56jfulHhL6u0CbNQ==/109951163023977355.jpg","authority":0,"mutual":false,"expertTags":null,"experts":null,"djStatus":10,"vipType":11,"remarkName":null,"avatarImgIdStr":"109951163029169199","backgroundImgIdStr":"109951163023977355","avatarImgId_str":"109951163029169199"},"tracks":[{"name":"航行","id":574824312,"pst":0,"t":0,"ar":[{"id":12002044,"name":"跳大海乐队","tns":[],"alias":[]}],"alia":[],"pop":100,"st":0,"rt":null,"fee":0,"v":4,"crbt":null,"cf":"","al":{"id":39750799,"name":"俱乐部少年","picUrl":"http://p1.music.126.net/KsvT-Y8gJrUMq6VxE5EKgw==/109951163368652251.jpg","tns":[],"pic_str":"109951163368652251","pic":109951163368652260},"dt":277943,"h":{"br":320000,"fid":0,"size":11120893,"vd":-2},"m":{"br":192000,"fid":0,"size":6672553,"vd":-2},"l":{"br":128000,"fid":0,"size":4448383,"vd":-2},"a":null,"cd":"","no":2,"rtUrl":null,"ftype":0,"rtUrls":[],"djId":0,"copyright":0,"s_id":0,"rtype":0,"rurl":null,"mst":9,"mv":0,"cp":0,"publishTime":1529366400000},{"name":"白昼萤火","id":477332380,"pst":0,"t":0,"ar":[{"id":12408001,"name":"完美倒立","tns":[],"alias":[]}],"alia":[],"pop":100,"st":0,"rt":null,"fee":8,"v":9,"crbt":null,"cf":"","al":{"id":35474100,"name":"完美倒立","picUrl":"http://p1.music.126.net/JJ5wDhvw-VHR7HrfsXqMAQ==/18538865557837597.jpg","tns":[],"pic_str":"18538865557837597","pic":18538865557837596},"dt":344961,"h":{"br":320000,"fid":0,"size":13801056,"vd":-0.69},"m":{"br":160000,"fid":0,"size":6900551,"vd":-0.24},"l":{"br":96000,"fid":0,"size":4140348,"vd":-0.29},"a":null,"cd":"1","no":2,"rtUrl":null,"ftype":0,"rtUrls":[],"djId":0,"copyright":0,"s_id":0,"rtype":0,"rurl":null,"mst":9,"mv":0,"cp":456010,"publishTime":1494345600007},{"name":"Burgundy Red","id":438462712,"pst":0,"t":0,"ar":[{"id":11074,"name":"落日飞车","tns":[],"alias":[]}],"alia":["勃艮第红"],"pop":100,"st":0,"rt":null,"fee":0,"v":30,"crbt":null,"cf":"","al":{"id":34923361,"name":"Jinji Kikko","picUrl":"http://p1.music.126.net/UWWcyf4Q-7F-4cIUh5NE1w==/18825838091725130.jpg","tns":[],"pic_str":"18825838091725130","pic":18825838091725130},"dt":377986,"h":{"br":320000,"fid":0,"size":15121807,"vd":-1},"m":{"br":192000,"fid":0,"size":9073102,"vd":-1},"l":{"br":128000,"fid":0,"size":6048749,"vd":-1},"a":null,"cd":"1","no":1,"rtUrl":null,"ftype":0,"rtUrls":[],"djId":0,"copyright":1,"s_id":0,"rtype":0,"rurl":null,"mst":9,"mv":0,"cp":14028,"publishTime":1456761600000},{"name":"妈妈，我...","id":139373,"pst":0,"t":0,"ar":[{"id":4721,"name":"朴树","tns":[],"alias":[]}],"alia":[],"pop":100,"st":0,"rt":"600902000001102505","fee":8,"v":23,"crbt":"4a7800486a78c3efbdb27a95009caa83","cf":"","al":{"id":13892,"name":"我去2000年","picUrl":"http://p1.music.126.net/QYI8P7bfmwUKxH3Kll95LQ==/18878614649179588.jpg","tns":[],"pic_str":"18878614649179588","pic":18878614649179588},"dt":256266,"h":{"br":320000,"fid":0,"size":10255688,"vd":-0.23},"m":{"br":160000,"fid":0,"size":5128375,"vd":-0.000265076},"l":{"br":96000,"fid":0,"size":3077449,"vd":-0.000265076},"a":null,"cd":"1","no":2,"rtUrl":null,"ftype":0,"rtUrls":[],"djId":0,"copyright":2,"s_id":0,"rtype":0,"rurl":null,"mst":9,"mv":0,"cp":0,"publishTime":915120000000},{"name":"Bling Bling Bling","id":406072144,"pst":0,"t":0,"ar":[{"id":11760,"name":"后海大鲨鱼","tns":[],"alias":[]}],"alia":[],"pop":100,"st":0,"rt":null,"fee":0,"v":15,"crbt":null,"cf":"","al":{"id":3316050,"name":"心要野","picUrl":"http://p1.music.126.net/Il00DtS3hP6fahyVcc_quA==/1366692955577181.jpg","tns":[],"pic":1366692955577181},"dt":284864,"h":{"br":320000,"fid":0,"size":11396745,"vd":-1.2},"m":{"br":160000,"fid":0,"size":5698395,"vd":-0.76},"l":{"br":96000,"fid":0,"size":3419054,"vd":-0.81},"a":null,"cd":"1","no":11,"rtUrl":null,"ftype":0,"rtUrls":[],"djId":0,"copyright":2,"s_id":0,"rtype":0,"rurl":null,"mst":9,"mv":0,"cp":22020,"publishTime":1457492371393},{"name":"月光舞厅","id":574825024,"pst":0,"t":0,"ar":[{"id":12002044,"name":"跳大海乐队","tns":[],"alias":[]}],"alia":[],"pop":100,"st":0,"rt":null,"fee":0,"v":4,"crbt":null,"cf":"","al":{"id":39750799,"name":"俱乐部少年","picUrl":"http://p1.music.126.net/KsvT-Y8gJrUMq6VxE5EKgw==/109951163368652251.jpg","tns":[],"pic_str":"109951163368652251","pic":109951163368652260},"dt":314172,"h":{"br":320000,"fid":0,"size":12569121,"vd":-3},"m":{"br":192000,"fid":0,"size":7541490,"vd":-3},"l":{"br":128000,"fid":0,"size":5027675,"vd":-2},"a":null,"cd":"","no":1,"rtUrl":null,"ftype":0,"rtUrls":[],"djId":0,"copyright":0,"s_id":0,"rtype":0,"rurl":null,"mst":9,"mv":0,"cp":0,"publishTime":1529366400000},{"name":"你在等什么？ What You Waiting For?","id":490602331,"pst":0,"t":0,"ar":[{"id":12079035,"name":"孔雀眼","tns":[],"alias":[]}],"alia":[],"pop":100,"st":0,"rt":null,"fee":8,"v":37,"crbt":null,"cf":"","al":{"id":35834433,"name":"迷恋 ADDICT","picUrl":"http://p1.music.126.net/cj08Vhggglt9HrReeC08Qw==/18788454697422670.jpg","tns":[],"pic_str":"18788454697422670","pic":18788454697422670},"dt":211013,"h":{"br":320000,"fid":0,"size":8442819,"vd":0},"m":{"br":192000,"fid":0,"size":5065709,"vd":0},"l":{"br":128000,"fid":0,"size":3377154,"vd":0},"a":null,"cd":"","no":8,"rtUrl":null,"ftype":0,"rtUrls":[],"djId":0,"copyright":0,"s_id":0,"rtype":0,"rurl":null,"mst":9,"mv":5592955,"cp":36016,"publishTime":1501430400007},{"name":"像一个漩涡","id":135009,"pst":0,"t":0,"ar":[{"id":4478,"name":"木玛&Third Party","tns":[],"alias":[]}],"alia":[],"pop":95,"st":0,"rt":"","fee":8,"v":26,"crbt":null,"cf":"","al":{"id":13350,"name":"进化","picUrl":"http://p1.music.126.net/Gnh2giNMjCAyyp8i3jj82A==/28587302323203.jpg","tns":[],"pic":28587302323203},"dt":327001,"h":{"br":320000,"fid":0,"size":13082010,"vd":-1.97},"m":{"br":160000,"fid":0,"size":6547087,"vd":-1.59},"l":{"br":96000,"fid":0,"size":3933171,"vd":-1.7},"a":null,"cd":"1","no":9,"rtUrl":null,"ftype":0,"rtUrls":[],"djId":0,"copyright":0,"s_id":0,"rtype":0,"rurl":null,"mst":9,"mv":0,"cp":489026,"publishTime":1324396800000},{"name":"平行世界的风","id":500913674,"pst":0,"t":0,"ar":[{"id":12384062,"name":"星号69","tns":[],"alias":[]}],"alia":[],"pop":95,"st":0,"rt":null,"fee":0,"v":8,"crbt":null,"cf":"","al":{"id":36037051,"name":"平行世界的风","picUrl":"http://p1.music.126.net/kGpIdQndQcJonN2WVQVd2Q==/109951163010073073.jpg","tns":[],"pic_str":"109951163010073073","pic":109951163010073070},"dt":257607,"h":{"br":320000,"fid":0,"size":10306917,"vd":-1},"m":{"br":192000,"fid":0,"size":6184168,"vd":-1},"l":{"br":128000,"fid":0,"size":4122793,"vd":-1},"a":null,"cd":"1","no":2,"rtUrl":null,"ftype":0,"rtUrls":[],"djId":0,"copyright":0,"s_id":0,"rtype":0,"rurl":null,"mst":9,"mv":5780005,"cp":33005,"publishTime":1503504000000},{"name":"优越的嘈杂","id":29740161,"pst":0,"t":0,"ar":[{"id":1032146,"name":"野外合作社","tns":[],"alias":[]}],"alia":[],"pop":95,"st":0,"rt":null,"fee":0,"v":17,"crbt":null,"cf":"","al":{"id":3053517,"name":"野外合作社","picUrl":"http://p1.music.126.net/iT4MyLj8uK2lI956p0my1g==/18633423557755193.jpg","tns":[],"pic_str":"18633423557755193","pic":18633423557755190},"dt":380002,"h":{"br":320000,"fid":0,"size":15202264,"vd":-3.26},"m":{"br":160000,"fid":0,"size":7601155,"vd":-2.84},"l":{"br":96000,"fid":0,"size":4560711,"vd":-2.88},"a":null,"cd":"1","no":4,"rtUrl":null,"ftype":0,"rtUrls":[],"djId":0,"copyright":1,"s_id":0,"rtype":0,"rurl":null,"mst":9,"mv":0,"cp":14028,"publishTime":1377964800000},{"name":"Don’t Give A Damn About Me!","id":185841,"pst":0,"t":0,"ar":[{"id":6453,"name":"张震岳","tns":[],"alias":[]}],"alia":[],"pop":95,"st":0,"rt":"","fee":8,"v":26,"crbt":null,"cf":"","al":{"id":18889,"name":"Orange 2","picUrl":"http://p1.music.126.net/lMpQgpq8ReljvqjP82kfEQ==/130841883718477.jpg","tns":[],"pic":130841883718477},"dt":459468,"h":{"br":320000,"fid":0,"size":18384261,"vd":-0.000265076},"m":{"br":160000,"fid":0,"size":9203266,"vd":-0.000265076},"l":{"br":96000,"fid":0,"size":5530450,"vd":-0.000265076},"a":null,"cd":"1","no":1,"rtUrl":null,"ftype":0,"rtUrls":[],"djId":0,"copyright":0,"s_id":0,"rtype":0,"rurl":null,"mst":9,"mv":0,"cp":684010,"publishTime":993916800000},{"name":"夜猫","id":454069877,"pst":0,"t":0,"ar":[{"id":12328,"name":"马赛克","tns":[],"alias":[]}],"alia":[],"pop":100,"st":0,"rt":null,"fee":0,"v":34,"crbt":null,"cf":"","al":{"id":35158731,"name":"NO CLUB","picUrl":"http://p1.music.126.net/3jcQG9gmqPF8G_SCxO50LA==/18752170813492148.jpg","tns":[],"pic_str":"18752170813492148","pic":18752170813492148},"dt":283770,"h":{"br":320000,"fid":0,"size":11353905,"vd":-1.43},"m":{"br":160000,"fid":0,"size":5676975,"vd":-0.99},"l":{"br":96000,"fid":0,"size":3406203,"vd":-1.03},"a":null,"cd":"1","no":2,"rtUrl":null,"ftype":0,"rtUrls":[],"djId":0,"copyright":2,"s_id":0,"rtype":0,"rurl":null,"mst":9,"mv":5434084,"cp":22020,"publishTime":1488902400007},{"name":"Glow in the dark","id":357094,"pst":0,"t":0,"ar":[{"id":11760,"name":"后海大鲨鱼","tns":[],"alias":[]}],"alia":[],"pop":95,"st":0,"rt":"","fee":0,"v":14,"crbt":null,"cf":"","al":{"id":35258,"name":"浪潮","picUrl":"http://p1.music.126.net/tVkkoELl98AYflMZ5Po-aw==/64871186054784.jpg","tns":["Wave"],"pic":64871186054784},"dt":252839,"h":{"br":320000,"fid":0,"size":10159571,"vd":-3.62},"m":{"br":160000,"fid":0,"size":5111479,"vd":-3.26},"l":{"br":96000,"fid":0,"size":3088348,"vd":-3.35},"a":null,"cd":"1","no":1,"rtUrl":null,"ftype":0,"rtUrls":[],"djId":0,"copyright":1,"s_id":0,"rtype":0,"rurl":null,"mst":9,"mv":0,"cp":22020,"publishTime":1288368000000},{"name":"Rough Sea","id":428642242,"pst":0,"t":0,"ar":[{"id":918003,"name":"大波浪","tns":[],"alias":[]}],"alia":[],"pop":95,"st":0,"rt":null,"fee":0,"v":11,"crbt":null,"cf":"","al":{"id":34874675,"name":"The Big Wave","picUrl":"http://p1.music.126.net/8aCSVxuRGM4dlJ9mTlxwTA==/3431575800218517.jpg","tns":[],"pic":3431575800218517},"dt":260000,"h":{"br":320000,"fid":0,"size":10403048,"vd":-1.29},"m":{"br":160000,"fid":0,"size":5201547,"vd":-0.88},"l":{"br":96000,"fid":0,"size":3120946,"vd":-1.01},"a":null,"cd":"1","no":8,"rtUrl":null,"ftype":0,"rtUrls":[],"djId":0,"copyright":0,"s_id":0,"rtype":0,"rurl":null,"mst":9,"mv":0,"cp":22020,"publishTime":1473004800007},{"name":"迷浪","id":28640149,"pst":0,"t":0,"ar":[{"id":11368,"name":"DA BANG","tns":[],"alias":[]}],"alia":[],"pop":95,"st":0,"rt":null,"fee":0,"v":34,"crbt":null,"cf":"","al":{"id":2865241,"name":"迷浪","picUrl":"http://p1.music.126.net/dmQbHG8sNbJZBEqDTTQgfA==/6013229092807803.jpg","tns":[],"pic":6013229092807803},"dt":371398,"h":{"br":320000,"fid":0,"size":14858493,"vd":0},"m":{"br":192000,"fid":0,"size":8915113,"vd":0},"l":{"br":128000,"fid":0,"size":5943423,"vd":0},"a":null,"cd":"1","no":1,"rtUrl":null,"ftype":0,"rtUrls":[],"djId":0,"copyright":2,"s_id":0,"rtype":0,"rurl":null,"mst":9,"mv":0,"cp":22020,"publishTime":1402329600007},{"name":"我们可以在一起","id":387571,"pst":0,"t":0,"ar":[{"id":13282,"name":"新裤子","tns":[],"alias":[]}],"alia":[],"pop":100,"st":0,"rt":"","fee":0,"v":13,"crbt":null,"cf":"","al":{"id":38397,"name":"野人也有爱","picUrl":"http://p1.music.126.net/JbgnPPhGX7Ca2L0bvJpGwQ==/25288767454180.jpg","tns":[],"pic":25288767454180},"dt":310680,"h":{"br":320000,"fid":0,"size":12432211,"vd":-0.42},"m":{"br":160000,"fid":0,"size":6216636,"vd":-0.01},"l":{"br":96000,"fid":0,"size":3730406,"vd":-0.04},"a":null,"cd":"1","no":11,"rtUrl":null,"ftype":0,"rtUrls":[],"djId":0,"copyright":1,"s_id":0,"rtype":0,"rurl":null,"mst":9,"mv":288111,"cp":22020,"publishTime":1226592000000},{"name":"猛犸","id":27510434,"pst":0,"t":0,"ar":[{"id":11760,"name":"后海大鲨鱼","tns":[],"alias":[]}],"alia":[],"pop":100,"st":0,"rt":"","fee":0,"v":35,"crbt":null,"cf":"","al":{"id":3316050,"name":"心要野","picUrl":"http://p1.music.126.net/Il00DtS3hP6fahyVcc_quA==/1366692955577181.jpg","tns":[],"pic":1366692955577181},"dt":304064,"h":{"br":320000,"fid":0,"size":12164745,"vd":-0.89},"m":{"br":160000,"fid":0,"size":6082395,"vd":-0.48},"l":{"br":96000,"fid":0,"size":3649454,"vd":-0.53},"a":null,"cd":"1","no":3,"rtUrl":null,"ftype":0,"rtUrls":[],"djId":0,"copyright":1,"s_id":0,"rtype":0,"rurl":null,"mst":9,"mv":5264094,"cp":22020,"publishTime":1457452800007},{"name":"乐园","id":390475,"pst":0,"t":0,"ar":[{"id":13419,"name":"与非门乐队","tns":[],"alias":[]}],"alia":[],"pop":95,"st":0,"rt":"","fee":0,"v":3,"crbt":null,"cf":"","al":{"id":38676,"name":"A逻辑","picUrl":"http://p1.music.126.net/cTjCDL0JvFB5w9wlDsnNUA==/25288767454166.jpg","tns":[],"pic":25288767454166},"dt":258273,"h":{"br":320000,"fid":0,"size":10350310,"vd":0.0433159},"m":{"br":160000,"fid":0,"size":5189560,"vd":0.196239},"l":{"br":96000,"fid":0,"size":3124841,"vd":0.139755},"a":null,"cd":"1","no":7,"rtUrl":null,"ftype":0,"rtUrls":[],"djId":0,"copyright":2,"s_id":0,"rtype":0,"rurl":null,"mst":9,"mv":0,"cp":0,"publishTime":1128096000000},{"name":"雾 岛 风 起 时","id":543529203,"pst":0,"t":0,"ar":[{"id":12071101,"name":"志国夜总会","tns":[],"alias":[]}],"alia":[],"pop":95,"st":0,"rt":null,"fee":0,"v":17,"crbt":null,"cf":"","al":{"id":37798980,"name":"星 影","picUrl":"http://p1.music.126.net/rEYpwlvcXxq0zJzBL9Jccg==/109951163174845120.jpg","tns":[],"pic_str":"109951163174845120","pic":109951163174845120},"dt":129384,"h":{"br":320000,"fid":0,"size":5177513,"vd":0},"m":{"br":192000,"fid":0,"size":3106525,"vd":0},"l":{"br":128000,"fid":0,"size":2071031,"vd":0},"a":null,"cd":"","no":1,"rtUrl":null,"ftype":0,"rtUrls":[],"djId":0,"copyright":2,"s_id":0,"rtype":0,"rurl":null,"mst":9,"mv":0,"cp":0,"publishTime":1520179218236},{"name":"忘记他","id":68288,"pst":0,"t":0,"ar":[{"id":7768,"name":"关淑怡","tns":[],"alias":[]}],"alia":["电影《堕落天使》插曲"],"pop":100,"st":0,"rt":"600902000005613743","fee":8,"v":8,"crbt":null,"cf":"","al":{"id":6654,"name":"堕落天使","picUrl":"http://p1.music.126.net/t8jj-QUxn3QZstvECbb64g==/42880953495299.jpg","tns":[],"pic":42880953495299},"dt":204931,"h":{"br":320000,"fid":0,"size":8221270,"vd":0.454364},"m":{"br":160000,"fid":0,"size":4126316,"vd":0.295772},"l":{"br":96000,"fid":0,"size":2487916,"vd":0.167816},"a":null,"cd":"1","no":20,"rtUrl":null,"ftype":0,"rtUrls":[],"djId":0,"copyright":1,"s_id":0,"rtype":0,"rurl":null,"mst":9,"mv":0,"cp":7003,"publishTime":799862400000},{"name":"悲伤的幻觉","id":348084,"pst":0,"t":0,"ar":[{"id":11236,"name":"超级市场","tns":[],"alias":[]}],"alia":[],"pop":95,"st":0,"rt":"","fee":0,"v":17,"crbt":null,"cf":"","al":{"id":34313,"name":"模样","picUrl":"http://p1.music.126.net/RD3hUpnUO4fjZjshdcPPJg==/91259465121375.jpg","tns":[],"pic":91259465121375},"dt":213969,"h":null,"m":null,"l":{"br":96000,"fid":0,"size":2590985,"vd":1.40475},"a":null,"cd":"1","no":2,"rtUrl":null,"ftype":0,"rtUrls":[],"djId":0,"copyright":1,"s_id":0,"rtype":0,"rurl":null,"mst":9,"mv":0,"cp":22020,"publishTime":899222400000},{"name":"伸手摘下了","id":32619801,"pst":0,"t":0,"ar":[{"id":4037,"name":"Lu1","tns":[],"alias":[]}],"alia":[],"pop":95,"st":0,"rt":null,"fee":0,"v":2,"crbt":null,"cf":"","al":{"id":3163110,"name":"伸手摘下了","picUrl":"http://p1.music.126.net/HJxBUq5WNKEKcF-n3f9Qhw==/7976956859919093.jpg","tns":[],"pic":7976956859919093},"dt":199000,"h":{"br":320000,"fid":0,"size":7964342,"vd":-3.18},"m":{"br":160000,"fid":0,"size":3982237,"vd":-2.74},"l":{"br":96000,"fid":0,"size":2389394,"vd":-2.8},"a":null,"cd":"1","no":1,"rtUrl":null,"ftype":0,"rtUrls":[],"djId":0,"copyright":0,"s_id":0,"rtype":0,"rurl":null,"mst":9,"mv":0,"cp":0,"publishTime":1434384000007},{"name":"都市青春恋曲","id":469744891,"pst":0,"t":0,"ar":[{"id":12355461,"name":"脆弱少女组","tns":[],"alias":[]}],"alia":[],"pop":95,"st":0,"rt":null,"fee":8,"v":7,"crbt":null,"cf":"","al":{"id":35326980,"name":"一些难过的时候可以听的流行歌曲","picUrl":"http://p1.music.126.net/Gk5lsAcMghmeZpC78zbg8A==/18901704393154231.jpg","tns":[],"pic_str":"18901704393154231","pic":18901704393154230},"dt":297531,"h":{"br":320000,"fid":0,"size":11903521,"vd":-0.000265076},"m":{"br":160000,"fid":0,"size":5951783,"vd":0},"l":{"br":96000,"fid":0,"size":3571088,"vd":-0.000265076},"a":null,"cd":"1","no":2,"rtUrl":null,"ftype":0,"rtUrls":[],"djId":0,"copyright":1,"s_id":0,"rtype":0,"rurl":null,"mst":9,"mv":0,"cp":36016,"publishTime":1491494400007},{"name":"我失去了她(Remix) - remix","id":365573,"pst":0,"t":0,"ar":[{"id":12260,"name":"木马","tns":[],"alias":[]}],"alia":[],"pop":95,"st":0,"rt":"","fee":0,"v":12,"crbt":null,"cf":"","al":{"id":36190,"name":"果冻帝国","picUrl":"http://p1.music.126.net/XS880Ned-yJHZKWkS8GtWA==/75866302329283.jpg","tns":[],"pic":75866302329283},"dt":247186,"h":{"br":320000,"fid":0,"size":9892074,"vd":-0.000265076},"m":{"br":160000,"fid":0,"size":4946573,"vd":-0.000265076},"l":{"br":96000,"fid":0,"size":2968372,"vd":-0.000265076},"a":null,"cd":"1","no":9,"rtUrl":null,"ftype":0,"rtUrls":[],"djId":0,"copyright":1,"s_id":0,"rtype":0,"rurl":null,"mst":9,"mv":0,"cp":22020,"publishTime":1093968000000},{"name":"今夜留给今夜吧","id":405599991,"pst":0,"t":0,"ar":[{"id":11760,"name":"后海大鲨鱼","tns":[],"alias":[]}],"alia":[],"pop":95,"st":0,"rt":null,"fee":0,"v":12,"crbt":null,"cf":"","al":{"id":3316050,"name":"心要野","picUrl":"http://p1.music.126.net/Il00DtS3hP6fahyVcc_quA==/1366692955577181.jpg","tns":[],"pic":1366692955577181},"dt":296499,"h":{"br":320000,"fid":0,"size":11862769,"vd":-0.18},"m":{"br":160000,"fid":0,"size":5931407,"vd":0},"l":{"br":96000,"fid":0,"size":3558862,"vd":-0.000265076},"a":null,"cd":"1","no":5,"rtUrl":null,"ftype":0,"rtUrls":[],"djId":0,"copyright":2,"s_id":0,"rtype":0,"rurl":null,"mst":9,"mv":0,"cp":22020,"publishTime":1457492601519},{"name":"Bye Bye","id":28168578,"pst":0,"t":0,"ar":[{"id":12111,"name":"旅行团","tns":[],"alias":[]}],"alia":[],"pop":95,"st":0,"rt":"","fee":0,"v":14,"crbt":null,"cf":"","al":{"id":2737250,"name":"于是我不再唱歌","picUrl":"http://p1.music.126.net/l4HPmVpNRL3U0bR0JQRuxQ==/5831809673869314.jpg","tns":[],"pic":5831809673869314},"dt":220499,"h":{"br":320000,"fid":0,"size":8828063,"vd":0},"m":{"br":160000,"fid":0,"size":4420684,"vd":0},"l":{"br":96000,"fid":0,"size":2657732,"vd":0},"a":null,"cd":"1","no":2,"rtUrl":null,"ftype":0,"rtUrls":[],"djId":0,"copyright":2,"s_id":0,"rtype":0,"rurl":null,"mst":9,"mv":0,"cp":22020,"publishTime":1388160000007},{"name":"蒸发的世界剩下我","id":524003502,"pst":0,"t":0,"ar":[{"id":1193482,"name":"原子邦妮","tns":[],"alias":[]}],"alia":["Alone In The Vaporized World"],"pop":95,"st":0,"rt":null,"fee":8,"v":17,"crbt":null,"cf":"","al":{"id":36875928,"name":"谢谢你曾经让我悲伤","picUrl":"http://p1.music.126.net/S6jOHOgD7LC_IJ7jXu9Xrw==/109951163085279660.jpg","tns":[],"pic_str":"109951163085279660","pic":109951163085279660},"dt":207216,"h":{"br":320000,"fid":0,"size":8290264,"vd":0},"m":{"br":192000,"fid":0,"size":4974176,"vd":0},"l":{"br":128000,"fid":0,"size":3316132,"vd":0},"a":null,"cd":"1","no":3,"rtUrl":null,"ftype":0,"rtUrls":[],"djId":0,"copyright":2,"s_id":0,"rtype":0,"rurl":null,"mst":9,"mv":0,"cp":684010,"publishTime":1513267200000},{"name":"我睡在你眼睛的沙漠里","id":390504,"pst":0,"t":0,"ar":[{"id":13419,"name":"与非门乐队","tns":[],"alias":[]}],"alia":[],"pop":100,"st":0,"rt":"","fee":0,"v":11,"crbt":null,"cf":"","al":{"id":38679,"name":"11","picUrl":"http://p1.music.126.net/XBqSBllLSELUkGW-ZCWumw==/101155069770319.jpg","tns":[],"pic":101155069770319},"dt":260101,"h":{"br":320000,"fid":0,"size":10424029,"vd":0},"m":{"br":160000,"fid":0,"size":5225663,"vd":0},"l":{"br":96000,"fid":0,"size":3146316,"vd":-0.000265076},"a":null,"cd":"1","no":4,"rtUrl":null,"ftype":0,"rtUrls":[],"djId":0,"copyright":1,"s_id":0,"rtype":0,"rurl":null,"mst":9,"mv":0,"cp":5003,"publishTime":1107792000007},{"name":"最后，我们会一起去海边","id":348074,"pst":0,"t":0,"ar":[{"id":11238,"name":"刺猬","tns":[],"alias":[]}],"alia":[],"pop":95,"st":0,"rt":"","fee":0,"v":32,"crbt":null,"cf":"","al":{"id":34310,"name":"甜蜜与杀害(Honeyed And Killed)","picUrl":"http://p1.music.126.net/mKk9pDtPD7SubCkdqHABpQ==/107752139534584.jpg","tns":[],"pic":107752139534584},"dt":373943,"h":{"br":320000,"fid":0,"size":14965246,"vd":-2.73},"m":{"br":160000,"fid":0,"size":7492658,"vd":-2.3},"l":{"br":96000,"fid":0,"size":4503205,"vd":-2.4},"a":null,"cd":"1","no":10,"rtUrl":null,"ftype":0,"rtUrls":[],"djId":0,"copyright":1,"s_id":0,"rtype":0,"rurl":null,"mst":9,"mv":5564529,"cp":22020,"publishTime":1299859200000},{"name":"Bye Bye Disco","id":387585,"pst":0,"t":0,"ar":[{"id":13282,"name":"新裤子","tns":[],"alias":[]}],"alia":[],"pop":95,"st":0,"rt":"","fee":0,"v":15,"crbt":null,"cf":"","al":{"id":38402,"name":"龙虎人丹","picUrl":"http://p1.music.126.net/no9fAGy3ZoGAD04mqq_Ovg==/126443837210722.jpg","tns":[],"pic":126443837210722},"dt":305000,"h":{"br":320000,"fid":0,"size":12281288,"vd":-3.79},"m":{"br":160000,"fid":0,"size":6163934,"vd":-3.35},"l":{"br":96000,"fid":0,"size":3716574,"vd":-3.39},"a":null,"cd":"1","no":2,"rtUrl":null,"ftype":0,"rtUrls":[],"djId":0,"copyright":1,"s_id":0,"rtype":0,"rurl":null,"mst":9,"mv":0,"cp":22020,"publishTime":1159632000000}],"trackIds":[{"id":574824312,"v":4},{"id":477332380,"v":9},{"id":438462712,"v":30},{"id":139373,"v":23},{"id":406072144,"v":15},{"id":574825024,"v":4},{"id":490602331,"v":37},{"id":135009,"v":26},{"id":500913674,"v":8},{"id":29740161,"v":17},{"id":185841,"v":26},{"id":454069877,"v":34},{"id":357094,"v":14},{"id":428642242,"v":11},{"id":28640149,"v":34},{"id":387571,"v":13},{"id":27510434,"v":35},{"id":390475,"v":3},{"id":543529203,"v":17},{"id":68288,"v":8},{"id":348084,"v":17},{"id":32619801,"v":2},{"id":469744891,"v":7},{"id":365573,"v":12},{"id":405599991,"v":12},{"id":28168578,"v":14},{"id":524003502,"v":17},{"id":390504,"v":11},{"id":348074,"v":32},{"id":387585,"v":15}],"updateTime":1532337875166,"commentThreadId":"A_PL_0_2323596120","coverImgUrl":"http://p1.music.126.net/f4rq2vrd2AQ1i8KDazRHhQ==/109951163421407852.jpg","tags":["华语","电子","孤独"],"playCount":6040834,"trackCount":30,"adType":0,"trackNumberUpdateTime":1532071668081,"createTime":1532060979007,"highQuality":true,"coverImgId":109951163421407860,"newImported":false,"specialType":0,"privacy":0,"subscribedCount":104386,"cloudTrackCount":0,"description":"我记得一些聚会散场后失落的人，有一次一个朋友在所有人面前抱着另一个朋友嚎啕大哭，这可吓坏了我们，我们从来没有见到他这样，暂且叫他A君吧，该怎么形容他呢，接受过良好的教育，有着大家羡慕的工作，女朋友很漂亮，在行业内大家都敬仰他…看起来这一切都没有问题，关键是，我们从来没有见到过这样的情形，因为无论什么场合，A君总是把大家和气氛照顾很好，这样一来我们也就有些束手无策，大家都在对他说着怎么了，没关系你说出来等等各种无关紧要的安慰话语，半个小时后，A君冷静下来，像什么都没发生过一样，然后大家各自离场，我却记得那个夜晚和A君的眼泪。 有很多次可能我也是这样的，在各种场合中滔滔不绝，面对自己的时候失语，在极度难过中拥抱自己，这种撕裂夹杂着矛盾和敏感，也许大部分的人都这样吧，边大声的笑着边给予自己安慰，白天严捂着悲伤，只有在夜里才会舔舐自己的伤口。 孤独，是我们来到这个世界必须要面对的功课。 当下人群中有一个新的词语叫做“人造开朗”，大概的指的是原本内向的人，在周围的环境与刺激下，做出了开朗的表现，与天生开朗的人不同的是，所谓的“人造开朗”是一种应激反应，在很多聚会与很多陌生人存在的场合里，这样的人群普遍存在，你觉得你是吗？ 很多年前看过一部日本电影讲的是一个小小的Club，深夜营业，需要情绪感应才能进入，他们只接受伤心的人，里面播放的歌也随着当天所有人的情绪值而不同，进去之后你才发现，从影视明星到小混混，从百万富翁到破产的中年人，从摇滚歌手到诗人，他们都混迹在这个Club里面，原来在孤独里，所有人都是平等的，于是有很多奇妙的事情就在这个“孤独俱乐部”里发生着，比如有让人返老还童的，有让人忘记回忆的DJ驻场…从某种程度上来讲，我觉得这样的深夜俱乐部比深夜食堂要治愈得多。 我梦到过这个场景好几次，在小小的Club里面，我成为里面的一员，音乐随着情绪起伏，现实变得迷离起来，有些许Club的电音节拍却渗透着悲喜，犹如那些聚会将要散场的失落，从一开始我们就踏入着这样的剧情，别被那些热烈蒙蔽了耳朵，Down到了最谷底也许才会奋力一跃的勇气，在沉醉的夜晚，欢迎进入“失落少年的孤独心俱乐部”。 「无谓着现在怜悯着过去足矣 挥霍着时间吝啬着自己最好 当繁星坠落，世界多美好」 ----跳大海《航行》 本期作者：何西 ","ordered":true,"status":0,"trackUpdateTime":1535884385973,"userId":289477415,"name":"失落少年孤独心俱乐部","id":2323596120,"shareCount":800,"coverImgId_str":"109951163421407852","commentCount":1025},"code":200,"privileges":[{"id":574824312,"fee":0,"payed":0,"st":0,"pl":320000,"dl":320000,"sp":7,"cp":1,"subp":1,"cs":false,"maxbr":999000,"fl":320000,"toast":false,"flag":128,"preSell":false},{"id":477332380,"fee":8,"payed":0,"st":0,"pl":128000,"dl":0,"sp":7,"cp":1,"subp":1,"cs":false,"maxbr":999000,"fl":128000,"toast":false,"flag":128,"preSell":false},{"id":438462712,"fee":0,"payed":0,"st":0,"pl":320000,"dl":320000,"sp":7,"cp":1,"subp":1,"cs":false,"maxbr":999000,"fl":320000,"toast":false,"flag":128,"preSell":false},{"id":139373,"fee":8,"payed":0,"st":0,"pl":128000,"dl":0,"sp":7,"cp":1,"subp":1,"cs":false,"maxbr":999000,"fl":128000,"toast":false,"flag":128,"preSell":false},{"id":406072144,"fee":0,"payed":0,"st":0,"pl":320000,"dl":320000,"sp":7,"cp":1,"subp":1,"cs":false,"maxbr":999000,"fl":320000,"toast":false,"flag":256,"preSell":false},{"id":574825024,"fee":0,"payed":0,"st":0,"pl":320000,"dl":320000,"sp":7,"cp":1,"subp":1,"cs":false,"maxbr":999000,"fl":320000,"toast":false,"flag":128,"preSell":false},{"id":490602331,"fee":8,"payed":0,"st":0,"pl":128000,"dl":0,"sp":7,"cp":1,"subp":1,"cs":false,"maxbr":999000,"fl":128000,"toast":false,"flag":128,"preSell":false},{"id":135009,"fee":8,"payed":0,"st":0,"pl":128000,"dl":0,"sp":7,"cp":1,"subp":1,"cs":false,"maxbr":320000,"fl":128000,"toast":false,"flag":128,"preSell":false},{"id":500913674,"fee":0,"payed":0,"st":0,"pl":320000,"dl":320000,"sp":7,"cp":1,"subp":1,"cs":false,"maxbr":999000,"fl":320000,"toast":false,"flag":128,"preSell":false},{"id":29740161,"fee":0,"payed":0,"st":0,"pl":320000,"dl":320000,"sp":7,"cp":1,"subp":1,"cs":false,"maxbr":999000,"fl":320000,"toast":false,"flag":130,"preSell":false},{"id":185841,"fee":8,"payed":0,"st":0,"pl":128000,"dl":0,"sp":7,"cp":1,"subp":1,"cs":false,"maxbr":320000,"fl":128000,"toast":false,"flag":128,"preSell":false},{"id":454069877,"fee":0,"payed":0,"st":0,"pl":320000,"dl":320000,"sp":7,"cp":1,"subp":1,"cs":false,"maxbr":999000,"fl":320000,"toast":false,"flag":256,"preSell":false},{"id":357094,"fee":0,"payed":0,"st":0,"pl":320000,"dl":320000,"sp":7,"cp":1,"subp":1,"cs":false,"maxbr":320000,"fl":320000,"toast":false,"flag":256,"preSell":false},{"id":428642242,"fee":0,"payed":0,"st":0,"pl":320000,"dl":320000,"sp":7,"cp":1,"subp":1,"cs":false,"maxbr":999000,"fl":320000,"toast":false,"flag":256,"preSell":false},{"id":28640149,"fee":0,"payed":0,"st":0,"pl":320000,"dl":320000,"sp":7,"cp":1,"subp":1,"cs":false,"maxbr":999000,"fl":320000,"toast":false,"flag":128,"preSell":false},{"id":387571,"fee":0,"payed":0,"st":0,"pl":320000,"dl":320000,"sp":7,"cp":1,"subp":1,"cs":false,"maxbr":999000,"fl":320000,"toast":false,"flag":256,"preSell":false},{"id":27510434,"fee":0,"payed":0,"st":0,"pl":320000,"dl":320000,"sp":7,"cp":1,"subp":1,"cs":false,"maxbr":999000,"fl":320000,"toast":false,"flag":256,"preSell":false},{"id":390475,"fee":0,"payed":0,"st":0,"pl":320000,"dl":320000,"sp":7,"cp":1,"subp":1,"cs":false,"maxbr":320000,"fl":320000,"toast":false,"flag":128,"preSell":false},{"id":543529203,"fee":0,"payed":0,"st":0,"pl":320000,"dl":320000,"sp":7,"cp":1,"subp":1,"cs":false,"maxbr":320000,"fl":320000,"toast":false,"flag":128,"preSell":false},{"id":68288,"fee":8,"payed":0,"st":0,"pl":128000,"dl":0,"sp":7,"cp":1,"subp":1,"cs":false,"maxbr":320000,"fl":128000,"toast":false,"flag":0,"preSell":false},{"id":348084,"fee":0,"payed":0,"st":0,"pl":96000,"dl":96000,"sp":7,"cp":1,"subp":1,"cs":false,"maxbr":96000,"fl":320000,"toast":false,"flag":256,"preSell":false},{"id":32619801,"fee":0,"payed":0,"st":0,"pl":320000,"dl":320000,"sp":7,"cp":1,"subp":1,"cs":false,"maxbr":320000,"fl":320000,"toast":false,"flag":0,"preSell":false},{"id":469744891,"fee":8,"payed":0,"st":0,"pl":128000,"dl":0,"sp":7,"cp":1,"subp":1,"cs":false,"maxbr":999000,"fl":128000,"toast":false,"flag":128,"preSell":false},{"id":365573,"fee":0,"payed":0,"st":0,"pl":320000,"dl":320000,"sp":7,"cp":1,"subp":1,"cs":false,"maxbr":999000,"fl":320000,"toast":false,"flag":256,"preSell":false},{"id":405599991,"fee":0,"payed":0,"st":0,"pl":320000,"dl":320000,"sp":7,"cp":1,"subp":1,"cs":false,"maxbr":999000,"fl":320000,"toast":false,"flag":256,"preSell":false},{"id":28168578,"fee":0,"payed":0,"st":0,"pl":320000,"dl":320000,"sp":7,"cp":1,"subp":1,"cs":false,"maxbr":320000,"fl":320000,"toast":false,"flag":256,"preSell":false},{"id":524003502,"fee":8,"payed":0,"st":0,"pl":128000,"dl":0,"sp":7,"cp":1,"subp":1,"cs":false,"maxbr":320000,"fl":128000,"toast":false,"flag":128,"preSell":false},{"id":390504,"fee":0,"payed":0,"st":0,"pl":320000,"dl":320000,"sp":7,"cp":1,"subp":1,"cs":false,"maxbr":320000,"fl":320000,"toast":false,"flag":128,"preSell":false},{"id":348074,"fee":0,"payed":0,"st":0,"pl":320000,"dl":320000,"sp":7,"cp":1,"subp":1,"cs":false,"maxbr":320000,"fl":320000,"toast":false,"flag":256,"preSell":false},{"id":387585,"fee":0,"payed":0,"st":0,"pl":320000,"dl":320000,"sp":7,"cp":1,"subp":1,"cs":false,"maxbr":320000,"fl":320000,"toast":false,"flag":256,"preSell":false}]}